pycman_dna/__init__.py
pycman_dna/map.py
pycman_dna/map_names.txt
pycman_dna/pacman_game.py
pycman_dna/images/PacmanDEAD.png
pycman_dna/images/PacmanDOWN.png
pycman_dna/images/PacmanLEFT.png
pycman_dna/images/PacmanRIGHT.png
pycman_dna/images/PacmanUP.png
pycman_dna/images/__init__.py
pycman_dna/images/dot.png
pycman_dna/images/eatable_ghost.png
pycman_dna/images/ghost.png
pycman_dna/images/icon.png
pycman_dna/images/pill.png
pycman_dna/images/wall.png
pycman_dna/maps/__init__.py
pycman_dna/maps/all_along_the_watchtowers.map
pycman_dna/maps/all_along_the_watchtowers_revisited.map
pycman_dna/maps/bimble.map
pycman_dna/maps/blank.map
pycman_dna/maps/broken_line_1.map
pycman_dna/maps/broken_line_2.map
pycman_dna/maps/broken_line_3.map
pycman_dna/maps/central_cavern.map
pycman_dna/maps/central_cavern_revisited.map
pycman_dna/maps/dizzy.map
pycman_dna/maps/easy_does_it.map
pycman_dna/maps/first_steps.map
pycman_dna/maps/follow_the_yellow_brick_road.map
pycman_dna/maps/ghost_train.map
pycman_dna/maps/i_smell_your_fear.map
pycman_dna/maps/impossible_to_solve_do_not_even_try.map
pycman_dna/maps/killing_time.map
pycman_dna/maps/maze.map
pycman_dna/maps/number_one_the_larch.map
pycman_dna/maps/on_the_outside.map
pycman_dna/maps/on_the_outside_revisited.map
pycman_dna/maps/ping_pong.map
pycman_dna/maps/ping_pong_revisited.map
pycman_dna/maps/sense_your_way.map
pycman_dna/maps/teeth.map
pycman_dna/maps/unbroken_line_1.map
pycman_dna/maps/unbroken_line_2.map
pycman_dna/maps/unbroken_line_3.map
pycman_dna/maps/valid_symbols.map
pycman_dna/maps/you_make_me_feel_like_dancing.map
pycman_dna/maps/you_will_blink_first.map
pycman_dna-1.0.1.dist-info/METADATA
pycman_dna-1.0.1.dist-info/WHEEL
pycman_dna-1.0.1.dist-info/top_level.txt
pycman_dna-1.0.1.dist-info/RECORD
