Metadata-Version: 2.1
Name: pycman-dna
Version: 1.0.1
Summary: Python Pacman Tool
Author: Liam Burns
Author-email: l.burns@dundeeandangus.ac.uk
Keywords: python,pacman
Classifier: Development Status :: 3 - Alpha
Classifier: Intended Audience :: Education
Classifier: Programming Language :: Python :: 2
Classifier: Programming Language :: Python :: 3
Classifier: Operating System :: MacOS :: MacOS X
Classifier: Operating System :: Microsoft :: Windows
Requires-Dist: pygame
